README.rst
setup.py
fix_chitown/__init__.py
fix_chitown/__main__.py
fix_chitown/utils.py
fix_chitown.egg-info/PKG-INFO
fix_chitown.egg-info/SOURCES.txt
fix_chitown.egg-info/dependency_links.txt
fix_chitown.egg-info/entry_points.txt
fix_chitown.egg-info/requires.txt
fix_chitown.egg-info/top_level.txt