Metadata-Version: 1.0
Name: fix-chitown
Version: 1.0.0
Summary: Fix Chicago team errors in the 2014 lahman DB.
Home-page: https://github.com/aitchslash
Author: Benjamin Field
Author-email: benjamin.field@gmail.com
License: MIT License
